wxyz/core/__init__.py
wxyz/core/_version.py
wxyz/core/base.py
wxyz/core/install.json
wxyz/core/widget_json.py
wxyz/core/js/LICENSE.txt
wxyz/core/js/README.md
wxyz/core/js/package.json
wxyz/core/labextension/package.json
wxyz/core/labextension/static/181.8803fa8ddaf585c955d4.js
wxyz/core/labextension/static/333.7772a68d861b438d3641.js
wxyz/core/labextension/static/484.da13d6d57dee1aca9000.js
wxyz/core/labextension/static/581.93e12d006b4953432684.js
wxyz/core/labextension/static/581.93e12d006b4953432684.js.LICENSE.txt
wxyz/core/labextension/static/96.b02f638714eeabbb5128.js
wxyz/core/labextension/static/remoteEntry.8862fb0689f158a3124d.js
wxyz/core/labextension/static/style.js
wxyz_core-0.5.1.data/data/share/jupyter/labextensions/@deathbeds/wxyz-core/install.json
wxyz_core-0.5.1.data/data/share/jupyter/labextensions/@deathbeds/wxyz-core/package.json
wxyz_core-0.5.1.data/data/share/jupyter/labextensions/@deathbeds/wxyz-core/static/181.8803fa8ddaf585c955d4.js
wxyz_core-0.5.1.data/data/share/jupyter/labextensions/@deathbeds/wxyz-core/static/333.7772a68d861b438d3641.js
wxyz_core-0.5.1.data/data/share/jupyter/labextensions/@deathbeds/wxyz-core/static/484.da13d6d57dee1aca9000.js
wxyz_core-0.5.1.data/data/share/jupyter/labextensions/@deathbeds/wxyz-core/static/581.93e12d006b4953432684.js
wxyz_core-0.5.1.data/data/share/jupyter/labextensions/@deathbeds/wxyz-core/static/581.93e12d006b4953432684.js.LICENSE.txt
wxyz_core-0.5.1.data/data/share/jupyter/labextensions/@deathbeds/wxyz-core/static/96.b02f638714eeabbb5128.js
wxyz_core-0.5.1.data/data/share/jupyter/labextensions/@deathbeds/wxyz-core/static/remoteEntry.8862fb0689f158a3124d.js
wxyz_core-0.5.1.data/data/share/jupyter/labextensions/@deathbeds/wxyz-core/static/style.js
wxyz_core-0.5.1.dist-info/LICENSE.txt
wxyz_core-0.5.1.dist-info/METADATA
wxyz_core-0.5.1.dist-info/WHEEL
wxyz_core-0.5.1.dist-info/top_level.txt
wxyz_core-0.5.1.dist-info/RECORD
